gallery_dl_wrap.py
gallery_dl_wrap-1.0.dist-info/METADATA
gallery_dl_wrap-1.0.dist-info/WHEEL
gallery_dl_wrap-1.0.dist-info/top_level.txt
gallery_dl_wrap-1.0.dist-info/RECORD
