Metadata-Version: 2.1
Name: gallery-dl-wrap
Version: 1.0
Summary: Wrapper to use gallery-dl inside python code.
Home-page: UNKNOWN
License: UNKNOWN
Platform: UNKNOWN
Requires-Dist: gallery-dl
